README.rst
setup.py
testsuite/__init__.py
testsuite/prettyprint/__init__.py
testsuite/prettyprint/outcomes/__init__.py
testsuite/prettyprint/outcomes/reporter.py
testsuite_prettyprint_outcomes.egg-info/PKG-INFO
testsuite_prettyprint_outcomes.egg-info/SOURCES.txt
testsuite_prettyprint_outcomes.egg-info/dependency_links.txt
testsuite_prettyprint_outcomes.egg-info/namespace_packages.txt
testsuite_prettyprint_outcomes.egg-info/requires.txt
testsuite_prettyprint_outcomes.egg-info/top_level.txt