Metadata-Version: 1.0
Name: testsuite-prettyprint-outcomes
Version: 0.1.0-alpha
Summary: testsuite-prettyprint-outcomes is a nose2 plugin that prettyprints test outcomes.
Home-page: UNKNOWN
Author: Omer Katz
Author-email: omer.drow@gmail.com
License: BSD3
Platform: UNKNOWN
